ttftree
