Metadata-Version: 1.0
Name: ttftree
Version: 0.2.4
Summary: A 2-3 finger tree library for Python
Home-page: UNKNOWN
Author: Alexander Boyd
Author-email: alex@opengroove.org
License: UNKNOWN
Platform: UNKNOWN
